fastorch/__init__.py
fastorch/functional.py
fastorch/models.py
fastorch/utils/__init__.py
fastorch/utils/data.py
fastorch/utils/toolkit.py
utils/__init__.py
utils/data.py
utils/toolkit.py
fastorch-0.0.2.dist-info/METADATA
fastorch-0.0.2.dist-info/WHEEL
fastorch-0.0.2.dist-info/top_level.txt
fastorch-0.0.2.dist-info/RECORD
